{
  "accountAssociation": {
    "header": "TODO_REPLACE_BASE64_HEADER",
    "payload": "TODO_REPLACE_BASE64_PAYLOAD",
    "signature": "TODO_REPLACE_BASE64_SIGNATURE"
  },
  "miniapp": {
    "version": "1",
    "name": "TheRektRunner",
    "homeUrl": "https://thererkt-runner.xyz/",
    "iconUrl": "https://thererkt-runner.xyz/assets/icon.png",
    "splashImageUrl": "https://thererkt-runner.xyz/assets/splash.png",
    "splashBackgroundColor": "#020617",
    "subtitle": "Run the volatility.",
    "description": "An infinite runner inside a trading chart. Volatility becomes terrain\u2014jump dumps, dodge bear traps, ride green candles.",
    "primaryCategory": "Games",
    "tags": [
      "fun",
      "simple",
      "utility"
    ],
    "heroImageUrl": "https://thererkt-runner.xyz/assets/hero.png",
    "ogTitle": "TheRektRunner",
    "ogDescription": "An infinite runner inside a trading chart. Volatility becomes terrain\u2014jump dumps, dodge bear traps, ride green candles.",
    "ogImageUrl": "https://thererkt-runner.xyz/assets/hero.png",
    "screenshotUrls": [
      "https://thererkt-runner.xyz/assets/hero.png"
    ],
    "noindex": true
  }
}
